algorhythm/__init__.py
algorhythm/chords_library.py
algorhythm/patternlayer.py
algorhythm/synth.py
algorhythm-1.0.0.dist-info/licenses/LICENSE.md
algorhythm-1.0.0.dist-info/METADATA
algorhythm-1.0.0.dist-info/WHEEL
algorhythm-1.0.0.dist-info/top_level.txt
algorhythm-1.0.0.dist-info/RECORD
