Metadata-Version: 2.4
Name: algorhythm
Version: 1.0.0
Summary: A Python library for real-time audio synthesis, pattern sequencing, and generative music.
Home-page: https://github.com/Niamhck/algorhythm
Author: Niamh Callinan Keenan
Author-email: Niamh Callinan Keenan <ncallinank@gmail.com>
License: MIT
Project-URL: Homepage, https://github.com/Niamhck/algorhythm
Project-URL: Source, https://github.com/Niamhck/algorhythm
Project-URL: Bug Tracker, https://github.com/Niamhck/algorhythm/issues
Classifier: Programming Language :: Python :: 3
Classifier: License :: OSI Approved :: MIT License
Classifier: Operating System :: OS Independent
Classifier: Topic :: Multimedia :: Sound/Audio :: Sound Synthesis
Classifier: Intended Audience :: Developers
Classifier: Intended Audience :: Science/Research
Classifier: Natural Language :: English
Requires-Python: >=3.7
License-File: LICENSE.md
Requires-Dist: numpy>=1.20.0
Requires-Dist: sounddevice>=0.4.0
Requires-Dist: scipy>=1.7.0
Dynamic: author
Dynamic: home-page
Dynamic: license-file
Dynamic: requires-python
